aws_cdk/aws_servicecatalog_alpha/__init__.py
aws_cdk/aws_servicecatalog_alpha/py.typed
aws_cdk/aws_servicecatalog_alpha/_jsii/__init__.py
aws_cdk/aws_servicecatalog_alpha/_jsii/aws-servicecatalog-alpha@2.22.0-alpha.0.jsii.tgz
aws_cdk.aws_servicecatalog_alpha-2.22.0a0.dist-info/LICENSE
aws_cdk.aws_servicecatalog_alpha-2.22.0a0.dist-info/METADATA
aws_cdk.aws_servicecatalog_alpha-2.22.0a0.dist-info/NOTICE
aws_cdk.aws_servicecatalog_alpha-2.22.0a0.dist-info/WHEEL
aws_cdk.aws_servicecatalog_alpha-2.22.0a0.dist-info/top_level.txt
aws_cdk.aws_servicecatalog_alpha-2.22.0a0.dist-info/RECORD
