Metadata-Version: 2.1
Name: aws-cdk.aws-servicecatalog-alpha
Version: 2.22.0a0
Summary: The CDK Construct Library for AWS::ServiceCatalog
Home-page: https://github.com/aws/aws-cdk
Author: Amazon Web Services
License: Apache-2.0
Project-URL: Source, https://github.com/aws/aws-cdk.git
Platform: UNKNOWN
Classifier: Intended Audience :: Developers
Classifier: Operating System :: OS Independent
Classifier: Programming Language :: JavaScript
Classifier: Programming Language :: Python :: 3 :: Only
Classifier: Programming Language :: Python :: 3.6
Classifier: Programming Language :: Python :: 3.7
Classifier: Programming Language :: Python :: 3.8
Classifier: Programming Language :: Python :: 3.9
Classifier: Typing :: Typed
Classifier: Development Status :: 4 - Beta
Classifier: License :: OSI Approved
Classifier: Framework :: AWS CDK
Classifier: Framework :: AWS CDK :: 2
Requires-Python: >=3.6
License-File: LICENSE
License-File: NOTICE
Requires-Dist: aws-cdk-lib (<3.0.0,>=2.22.0)
Requires-Dist: constructs (<11.0.0,>=10.0.0)
Requires-Dist: jsii (<2.0.0,>=1.57.0)
Requires-Dist: publication (>=0.0.3)
